[
    {
        "_id": "53fcaa123638c96ae7f7ce5b",
        "date": "2014-08-01",
        "page_id": 1207915,
        "performance": 5.566,
        "count": 481,
        "availability": 100,
        "unit": "ATC",
        "page": "Certified Car Research"
    },
    {
        "_id": "53fcaa123638c96ae7f7d8bd",
        "date": "2014-08-02",
        "page_id": 1207915,
        "performance": 4.885,
        "count": 481,
        "availability": 98.97,
        "unit": "ATC",
        "page": "Certified Car Research"
    },
    {
        "_id": "53fcaa123638c96ae7f7d8f5",
        "date": "2014-08-03",
        "page_id": 1207915,
        "performance": 5.297,
        "count": 484,
        "availability": 100,
        "unit": "ATC",
        "page": "Certified Car Research"
    },
    {
        "_id": "53fcaa123638c96ae7f7d92d",
        "date": "2014-08-04",
        "page_id": 1207915,
        "performance": 5.866,
        "count": 470,
        "availability": 97.51,
        "unit": "ATC",
        "page": "Certified Car Research"
    },
    {
        "_id": "53fcaa123638c96ae7f7d965",
        "date": "2014-08-05",
        "page_id": 1207915,
        "performance": 6.445,
        "count": 427,
        "availability": 99.53,
        "unit": "ATC",
        "page": "Certified Car Research"
    },
    {
        "_id": "53fcaa123638c96ae7f7d99d",
        "date": "2014-08-08",
        "page_id": 1207915,
        "performance": 4.204,
        "count": 476,
        "availability": 99.79,
        "unit": "ATC",
        "page": "Certified Car Research"
    },
    {
        "_id": "53fcaa123638c96ae7f7d9be",
        "date": "2014-08-06",
        "page_id": 1207915,
        "performance": 5.775,
        "count": 463,
        "availability": 95.46,
        "unit": "ATC",
        "page": "Certified Car Research"
    },
    {
        "_id": "53fcaa123638c96ae7f7da20",
        "date": "2014-08-10",
        "page_id": 1207915,
        "performance": 4.385,
        "count": 466,
        "availability": 98.94,
        "unit": "ATC",
        "page": "Certified Car Research"
    },
    {
        "_id": "53fcaa123638c96ae7f7da25",
        "date": "2014-08-07",
        "page_id": 1207915,
        "performance": 4.552,
        "count": 479,
        "availability": 100,
        "unit": "ATC",
        "page": "Certified Car Research"
    },
    {
        "_id": "53fcaa123638c96ae7f7da5d",
        "date": "2014-08-09",
        "page_id": 1207915,
        "performance": 4.842,
        "count": 470,
        "availability": 98.74,
        "unit": "ATC",
        "page": "Certified Car Research"
    },
    {
        "_id": "53fcaa123638c96ae7f7daa5",
        "date": "2014-08-11",
        "page_id": 1207915,
        "performance": 4.145,
        "count": 465,
        "availability": 98.31,
        "unit": "ATC",
        "page": "Certified Car Research"
    },
    {
        "_id": "53fcaa123638c96ae7f7dadd",
        "date": "2014-08-12",
        "page_id": 1207915,
        "performance": 5.062,
        "count": 446,
        "availability": 99.55,
        "unit": "ATC",
        "page": "Certified Car Research"
    },
    {
        "_id": "53fcaa123638c96ae7f7db29",
        "date": "2014-08-13",
        "page_id": 1207915,
        "performance": 5.175,
        "count": 477,
        "availability": 99.38,
        "unit": "ATC",
        "page": "Certified Car Research"
    },
    {
        "_id": "53fcaa123638c96ae7f7ef86",
        "date": "2014-08-14",
        "page_id": 1207915,
        "performance": 4.647,
        "count": 464,
        "availability": 99.78,
        "unit": "ATC",
        "page": "Certified Car Research"
    },
    {
        "_id": "53fcaa123638c96ae7f7efbc",
        "date": "2014-08-16",
        "page_id": 1207915,
        "performance": 4.154,
        "count": 473,
        "availability": 98.13,
        "unit": "ATC",
        "page": "Certified Car Research"
    },
    {
        "_id": "53fcaa123638c96ae7f7f012",
        "date": "2014-08-25",
        "page_id": 1207915,
        "performance": 4.502,
        "count": 465,
        "availability": 99.36,
        "unit": "ATC",
        "page": "Certified Car Research"
    },
    {
        "_id": "53fcaa123638c96ae7f7f05a",
        "date": "2014-08-17",
        "page_id": 1207915,
        "performance": 4.908,
        "count": 470,
        "availability": 98.74,
        "unit": "ATC",
        "page": "Certified Car Research"
    },
    {
        "_id": "53fcaa123638c96ae7f7f092",
        "date": "2014-08-15",
        "page_id": 1207915,
        "performance": 4.333,
        "count": 475,
        "availability": 99.58,
        "unit": "ATC",
        "page": "Certified Car Research"
    },
    {
        "_id": "53fcaa123638c96ae7f7f0ca",
        "date": "2014-08-19",
        "page_id": 1207915,
        "performance": 4.88,
        "count": 469,
        "availability": 99.58,
        "unit": "ATC",
        "page": "Certified Car Research"
    },
    {
        "_id": "53fcaa123638c96ae7f7f102",
        "date": "2014-08-18",
        "page_id": 1207915,
        "performance": 4.6,
        "count": 472,
        "availability": 99.16,
        "unit": "ATC",
        "page": "Certified Car Research"
    },
    {
        "_id": "53fcaa123638c96ae7f7f13a",
        "date": "2014-08-20",
        "page_id": 1207915,
        "performance": 4.981,
        "count": 467,
        "availability": 99.36,
        "unit": "ATC",
        "page": "Certified Car Research"
    },
    {
        "_id": "53fcaa123638c96ae7f7f174",
        "date": "2014-08-21",
        "page_id": 1207915,
        "performance": 4.791,
        "count": 477,
        "availability": 100,
        "unit": "ATC",
        "page": "Certified Car Research"
    },
    {
        "_id": "53fcaa123638c96ae7f7f1aa",
        "date": "2014-08-22",
        "page_id": 1207915,
        "performance": 4.665,
        "count": 474,
        "availability": 99.58,
        "unit": "ATC",
        "page": "Certified Car Research"
    },
    {
        "_id": "53fcaa123638c96ae7f7f1e2",
        "date": "2014-08-24",
        "page_id": 1207915,
        "performance": 4.455,
        "count": 469,
        "availability": 98.74,
        "unit": "ATC",
        "page": "Certified Car Research"
    },
    {
        "_id": "53fcaa123638c96ae7f7f21a",
        "date": "2014-08-23",
        "page_id": 1207915,
        "performance": 4.576,
        "count": 474,
        "availability": 99.37,
        "unit": "ATC",
        "page": "Certified Car Research"
    },
    {
        "_id": "53fdd17b00137a799885a08d",
        "count": 479,
        "name": "ATC Certified Car Research-IE (TxP)[IE] - Time to Interactive Page (seconds)[Median]",
        "date": "2014-08-26",
        "performance": 4.806,
        "page_id": 1207915,
        "availability": 99.17,
        "unit": "ATC",
        "page": "Certified Car Research"
    },
    {
        "_id": "53ff13e400137a2eca85151b",
        "count": 465,
        "name": "ATC Certified Car Research-IE (TxP)[IE] - Time to Interactive Page (seconds)[Median]",
        "date": "2014-08-27",
        "performance": 4.227,
        "page_id": 1207915,
        "availability": 97.48,
        "unit": "ATC",
        "page": "Certified Car Research"
    },
    {
        "_id": "5405e1b000137a423f1cf478",
        "count": 463,
        "name": "ATC Certified Car Research-IE (TxP)[IE] - Time to Interactive Page (seconds)[Median]",
        "date": "2014-09-01",
        "performance": 5.216,
        "page_id": 1207915,
        "availability": 99.78,
        "unit": "ATC",
        "page": "Certified Car Research"
    },
    {
        "_id": "5405e1f200137a4283dda5d1",
        "count": 458,
        "name": "ATC Certified Car Research-IE (TxP)[IE] - Time to Interactive Page (seconds)[Median]",
        "date": "2014-08-28",
        "performance": 4.138,
        "page_id": 1207915,
        "availability": 96.62,
        "unit": "ATC",
        "page": "Certified Car Research"
    },
    {
        "_id": "5405e22700137a42c35959ba",
        "count": 474,
        "name": "ATC Certified Car Research-IE (TxP)[IE] - Time to Interactive Page (seconds)[Median]",
        "date": "2014-08-29",
        "performance": 4.196,
        "page_id": 1207915,
        "availability": 98.75,
        "unit": "ATC",
        "page": "Certified Car Research"
    },
    {
        "_id": "5405e26800137a43044c63c9",
        "count": 473,
        "name": "ATC Certified Car Research-IE (TxP)[IE] - Time to Interactive Page (seconds)[Median]",
        "date": "2014-08-30",
        "performance": 3.949,
        "page_id": 1207915,
        "availability": 99.58,
        "unit": "ATC",
        "page": "Certified Car Research"
    },
    {
        "_id": "5405e2fa00137a435a273fa0",
        "count": 469,
        "name": "ATC Certified Car Research-IE (TxP)[IE] - Time to Interactive Page (seconds)[Median]",
        "date": "2014-08-31",
        "performance": 4.669,
        "page_id": 1207915,
        "availability": 99.79,
        "unit": "ATC",
        "page": "Certified Car Research"
    },
    {
        "_id": "54070f0300137a745c489b25",
        "count": 476,
        "name": "ATC Certified Car Research-IE (TxP)[IE] - Time to Interactive Page (seconds)[Median]",
        "date": "2014-09-02",
        "performance": 5.665,
        "page_id": 1207915,
        "availability": 100,
        "unit": "ATC",
        "page": "Certified Car Research"
    }
]